Hiven/client.py
Hiven/main.py
Hiven/Events/events.py
Hiven/Methods/get_user.py
Hiven/Methods/ping.py
Hiven/Methods/send.py
Hiven/Objects/bot_user.py
Hiven/Objects/house.py
Hiven/Objects/member_enter.py
Hiven/Objects/member_exit.py
Hiven/Objects/message.py
Hiven/Objects/message_update.py
Hiven/Objects/typing.py
Hiven/Websocket/websocket_handler.py
hivenpy-1.25.0.dist-info/LICENSE
hivenpy-1.25.0.dist-info/METADATA
hivenpy-1.25.0.dist-info/WHEEL
hivenpy-1.25.0.dist-info/top_level.txt
hivenpy-1.25.0.dist-info/RECORD
