Metadata-Version: 2.1
Name: hivenpy
Version: 1.25.0
Summary: An unofficial wrapper for hiven
Home-page: https://github.com/NexInfinite/hivenpy/
Author: Julian Jones
Author-email: julianjones663@gmail.com
License: UNKNOWN
Platform: UNKNOWN
Classifier: Programming Language :: Python :: 3
Classifier: License :: OSI Approved :: MIT License
Classifier: Operating System :: OS Independent
Requires-Dist: websocket-client
Requires-Dist: requests
Requires-Dist: ping3
